finae/__init__.py
finae/__main__.py
finae/core.py
finae/llm.py
finae/parser.py
finae/tot.py
finae/builtin/__init__.py
finae/builtin/__main__.py
finae/builtin/builtin.py
finae/builtin/integer.py
finae/legacy/exercise.py
finae/legacy/learn.py
finae/legacy/example/foo.py
finae/legacy/example/simple_math.py
finae-0.0.2.dist-info/LICENSE.txt
finae-0.0.2.dist-info/METADATA
finae-0.0.2.dist-info/WHEEL
finae-0.0.2.dist-info/entry_points.txt
finae-0.0.2.dist-info/top_level.txt
finae-0.0.2.dist-info/RECORD
