Metadata-Version: 2.1
Name: finae
Version: 0.0.2
Summary: A simple Python library
Author-email: Ning Ren <renning22@gmail.com>
Maintainer-email: Ning Ren <renning22@gmail.com>
Project-URL: Homepage, https://github.com/finae/py-finae
Project-URL: Bug Reports, https://github.com/finae/py-finae/issues
Project-URL: Funding, https://github.com/finae/py-finae
Project-URL: Say Thanks!, https://github.com/finae/py-finae
Project-URL: Source, https://github.com/finae/py-finae
Keywords: setuptools,development
Classifier: Development Status :: 3 - Alpha
Classifier: Intended Audience :: Developers
Classifier: Topic :: Software Development :: Build Tools
Classifier: License :: OSI Approved :: MIT License
Classifier: Programming Language :: Python :: 3
Classifier: Programming Language :: Python :: 3.7
Classifier: Programming Language :: Python :: 3.8
Classifier: Programming Language :: Python :: 3.9
Classifier: Programming Language :: Python :: 3.10
Classifier: Programming Language :: Python :: 3.11
Classifier: Programming Language :: Python :: 3 :: Only
Requires-Python: >=3.7
License-File: LICENSE.txt
Requires-Dist: langchain
Requires-Dist: openai
Requires-Dist: ray[default] ==2.6.0
Provides-Extra: dev
Requires-Dist: check-manifest ; extra == 'dev'
Provides-Extra: test
Requires-Dist: coverage ; extra == 'test'
